.gitignore
CHANGELOG.md
DEBUG.md
INSTALL.md
LICENSE
README.md
TODO.md
requirements.txt
setup.cfg
setup.py
tox.ini
tests/__init__.py
tests/test_api.py
tests/test_migration.py
zcm/__init__.py
zcm/__main__.py
zcm/exceptions.py
zcm/version.py
zcm/api/__init__.py
zcm/api/clone.py
zcm/api/manager.py
zcm/cli/__init__.py
zcm/cli/activate.py
zcm/cli/clone.py
zcm/cli/destroy.py
zcm/cli/difference.py
zcm/cli/information.py
zcm/cli/initialize.py
zcm/cli/list.py
zcm/cli/main.py
zcm/cli/remove.py
zcm/lib/__init__.py
zcm/lib/helpers.py
zcm/lib/print.py
zcm/lib/zfs.py
zfs_clone_manager.egg-info/PKG-INFO
zfs_clone_manager.egg-info/SOURCES.txt
zfs_clone_manager.egg-info/dependency_links.txt
zfs_clone_manager.egg-info/entry_points.txt
zfs_clone_manager.egg-info/not-zip-safe
zfs_clone_manager.egg-info/top_level.txt