Metadata-Version: 2.1
Name: zfs-clone-manager
Version: 3.4.0
Summary: Tool to manage ZFS clones with history metadata
Home-page: http://www.github.com/guillermomolina/zfs-clone-manager
Author: Guillermo Adrián Molina
Author-email: guillermoadrianmolina@hotmail.com
Maintainer: Guillermo Adrián Molina
Maintainer-email: guillermoadrianmolina@hotmail.com
License: LICENSE
Keywords: zfs
Platform: UNKNOWN
Classifier: Development Status :: 5 - Production/Stable
Classifier: Intended Audience :: Developers
Classifier: Intended Audience :: System Administrators
Classifier: License :: OSI Approved :: Apache Software License
Classifier: Operating System :: Unix
Classifier: Programming Language :: Python :: 3.7
Classifier: Topic :: Software Development :: Libraries :: Python Modules
Classifier: Topic :: System :: Operating System
